LICENSE.txt
README.md
setup.cfg
setup.py
defi/__init__.py
defi/defi_tools.py
defi.egg-info/PKG-INFO
defi.egg-info/SOURCES.txt
defi.egg-info/dependency_links.txt
defi.egg-info/requires.txt
defi.egg-info/top_level.txt