Metadata-Version: 2.1
Name: defi
Version: 1.0.18
Summary: UNKNOWN
Home-page: https://github.com/gauss314/defi
Author: Juan Pablo Pisano
Author-email: jpp.programacion@gmail.com
License: UNKNOWN
Keywords: defi,impermanent loss,finance,cryptos,bitcoin,liquidity pool,farming,bsc,eth,terra,heco,blockchain
Platform: UNKNOWN
Classifier: Programming Language :: Python :: 3
Classifier: License :: OSI Approved :: MIT License
Classifier: Operating System :: OS Independent
Requires-Python: >=3.6
License-File: LICENSE.txt
